faapi/__init__.py
faapi/__version__.py
faapi/base.py
faapi/comment.py
faapi/connection.py
faapi/exceptions.py
faapi/journal.py
faapi/parse.py
faapi/submission.py
faapi/user.py
faapi-3.11.14.dist-info/LICENSE
faapi-3.11.14.dist-info/WHEEL
faapi-3.11.14.dist-info/METADATA
faapi-3.11.14.dist-info/RECORD
