Metadata-Version: 2.1
Name: faapi
Version: 3.11.14
Summary: Python module to implement API-like functionality for the FurAffinity.net website.
Home-page: https://github.com/FurryCoders/FAAPI
License: EUPL-1.2
Author: Matteo Campinoti
Author-email: matteo.campinoti94@gmail.com
Requires-Python: >=3.9,<4.0
Classifier: Development Status :: 5 - Production/Stable
Classifier: Intended Audience :: Developers
Classifier: License :: OSI Approved :: European Union Public Licence 1.2 (EUPL 1.2)
Classifier: Operating System :: OS Independent
Classifier: Programming Language :: Python :: 3
Classifier: Programming Language :: Python :: 3.9
Classifier: Programming Language :: Python :: 3.10
Classifier: Programming Language :: Python :: 3.11
Classifier: Programming Language :: Python :: 3.10
Classifier: Programming Language :: Python :: 3.9
Classifier: Topic :: Internet :: WWW/HTTP :: Indexing/Search
Classifier: Typing :: Typed
Requires-Dist: bbcode (>=1.1.0,<2.0.0)
Requires-Dist: beautifulsoup4 (>=4.14.2,<5.0.0)
Requires-Dist: lxml (>=6.0.2,<7.0.0)
Requires-Dist: python-dateutil (>=2.9.0,<3.0.0)
Requires-Dist: requests (>=2.32.5,<3.0.0)
Project-URL: Bug Reports, https://github.com/FurryCoders/FAAPI/issues
Project-URL: Changelog, https://github.com/FurryCoders/FAAPI/blob/main/CHANGELOG.md
Project-URL: Download, https://pypi.org/project/faapi/#files
Project-URL: Repository, https://github.com/FurryCoders/FAAPI
Project-URL: Source, https://github.com/FurryCoders/FAAPI
